eight2/__init__.py
eight2/__main__.py
eight2/const.py
eight2/eight2.py
eight2/rulus.py
eight2/tools.py
eight2-0.2.0.dist-info/AUTHORS.rst
eight2-0.2.0.dist-info/LICENSE
eight2-0.2.0.dist-info/METADATA
eight2-0.2.0.dist-info/WHEEL
eight2-0.2.0.dist-info/entry_points.txt
eight2-0.2.0.dist-info/top_level.txt
eight2-0.2.0.dist-info/RECORD
