Metadata-Version: 2.1
Name: eight2
Version: 0.2.0
Summary: Python Boilerplate contains all the boilerplate you need to create a Python package.
Home-page: https://github.com/bopo/eight2
Author: eight2
Author-email: ibopo@126.com
License: MIT license
Keywords: eight2
Platform: UNKNOWN
Classifier: Development Status :: 2 - Pre-Alpha
Classifier: Intended Audience :: Developers
Classifier: License :: OSI Approved :: MIT License
Classifier: Natural Language :: English
Classifier: Programming Language :: Python :: 3
Classifier: Programming Language :: Python :: 3.5
Classifier: Programming Language :: Python :: 3.6
Classifier: Programming Language :: Python :: 3.7
Classifier: Programming Language :: Python :: 3.8
Requires-Python: >=3.6
Requires-Dist: tzlocal
Requires-Dist: jinja2
Requires-Dist: arrow
Requires-Dist: sxtwl
Requires-Dist: click
